rac_api_client/__init__.py
rac_api_client/client.py
rac_api_client-0.1.1.dist-info/LICENSE.md
rac_api_client-0.1.1.dist-info/METADATA
rac_api_client-0.1.1.dist-info/WHEEL
rac_api_client-0.1.1.dist-info/top_level.txt
rac_api_client-0.1.1.dist-info/RECORD
