Metadata-Version: 2.1
Name: rac-api-client
Version: 0.1.1
Summary: A client to interact with the Rockefeller Archive Center's Collections API.
Home-page: https://github.com/RockefellerArchiveCenter/rac_api_client
Author: Rockefeller Archive Center
Author-email: archive@rockarch.org
License: MIT
Platform: UNKNOWN
Classifier: Programming Language :: Python :: 3
Classifier: Intended Audience :: Other Audience
Classifier: License :: OSI Approved :: MIT License
Requires-Python: >=3.6
License-File: LICENSE.md
Requires-Dist: requests
